bookreturncalculatorPkg/__init__.py
bookreturncalculatorPkg/bookreturncalculator.py
bookreturncalculator-0.0.2.dist-info/LICENSE
bookreturncalculator-0.0.2.dist-info/METADATA
bookreturncalculator-0.0.2.dist-info/WHEEL
bookreturncalculator-0.0.2.dist-info/top_level.txt
bookreturncalculator-0.0.2.dist-info/RECORD
