Metadata-Version: 2.2
Name: bookreturncalculator
Version: 0.0.2
Summary: A library for calculating book return due dates.
Author: Alfi
Author-email: alfithomas2002@gmail.com
Classifier: Programming Language :: Python :: 3
Classifier: License :: OSI Approved :: MIT License
Classifier: Operating System :: OS Independent
Requires-Python: >=3.6
License-File: LICENSE
Dynamic: author
Dynamic: author-email
Dynamic: classifier
Dynamic: description-content-type
Dynamic: requires-python
Dynamic: summary
